LICENSE
MANIFEST.in
README.rst
setup.cfg
setup.py
gql_checker/__about__.py
gql_checker/__init__.py
gql_checker/flake8_linter.py
gql_checker/pylama_linter.py
gql_checker/stdlib_list.py
gql_checker.egg-info/PKG-INFO
gql_checker.egg-info/SOURCES.txt
gql_checker.egg-info/dependency_links.txt
gql_checker.egg-info/entry_points.txt
gql_checker.egg-info/not-zip-safe
gql_checker.egg-info/requires.txt
gql_checker.egg-info/top_level.txt
tests/__init__.py
tests/introspection_schema.json
tests/test_flake8_linter.py
tests/test_pylama_linter.py
tests/utils.py
tests/test_cases/bad_query.py
tests/test_cases/noqa.py
tests/test_cases/syntax_error.py
tests/test_cases/validation.py