Metadata-Version: 1.1
Name: gql-checker
Version: 0.1
Summary: Flake8 and pylama plugin that checks gql GraphQL calls.
Home-page: https://github.com/graphql-python/gql-checker
Author: Syrus Akbary
Author-email: me@syrusakbary.com
License: MIT
Platform: UNKNOWN
Classifier: Intended Audience :: Developers
Classifier: Development Status :: 4 - Beta
Classifier: License :: OSI Approved :: MIT License
Classifier: Programming Language :: Python
Classifier: Programming Language :: Python :: 2
Classifier: Programming Language :: Python :: 3
Classifier: License :: OSI Approved :: GNU Lesser General Public License v3 (LGPLv3)
Classifier: Topic :: Software Development :: Libraries :: Python Modules
Classifier: Topic :: Software Development :: Quality Assurance
Classifier: Operating System :: OS Independent
